<?xml version="1.0" encoding="UTF-8"?>
<procedure xmlns:dc="http://www.purl.org/dc/elements/1.1/" xmlns:rdf="http://www.w3.org/1999/02/22-rdf-syntax-ns#" xmlns:xlink="http://www.w3.org/1999/xlink" xmlns:xsi="http://www.w3.org/2001/XMLSchema-instance" xsi:noNamespaceSchemaLocation="http://www.s1000d.org/S1000D_6/xml_schema_flat/proced.xsd">
  <title>Bicycle Cleaning Procedure (DMC-S1000DBIKE-AAA-D00-00-00-00AA-258A-A_011-00_EN-US_1_1)</title>
  <description>This document details the procedure for cleaning a bicycle, ensuring optimal maintenance and performance.</description>
  <step id="step_1">
    <step_no>1</step_no>
    <step_title>Introduction</step_title>
    <step_description>This document outlines the procedure for cleaning a bicycle, ensuring optimal maintenance and performance.</step_description>
  </step>
  <step id="step_2">
    <step_no>2</step_no>
    <step_title>Prerequisites</step_title>
    <substep id="substep_2_1">
      <substep_no>2.1</substep_no>
      <substep_title>Tools &amp; Materials</substep_title>
      <items>
        <item>Water hose</item>
        <item>Brush (for scrubbing)</item>
        <item>Sponge</item>
        <item>Screwdriver (small blade)</item>
        <item>Detergent (various types depending on application - see Supplies section)</item>
        <item>Lubricant (refer to Data Module for specific lubricant information)</item>
      </items>
    </substep>
    <substep id="substep_2_2">
      <substep_no>2.2</substep_no>
      <substep_title>Safety Precautions</substep_title>
      <items>
        <item>Avoid getting detergents into your eyes. If contact occurs, flush immediately with clean, warm water.</item>
        <item>Do not use a high-pressure water hose, as it may damage bicycle components.</item>
        <item>Avoid directing the water hose directly at the hub or bottom bracket bearings.</item>
        <item>Apply detergents in accordance with the container instructions. Incorrect application may damage the bicycle paint.</item>
      </items>
    </substep>
  </step>
  <step id="step_3">
    <step_no>3</step_no>
    <step_title>Supplies</step_title>
    <items>
      <item>
        <item_name>Detergent 1</item_name>
        <item_description>(General cleaning, used with application 002)</item_description>
      </item>
      <item>
        <item_name>Detergent 2</item_name>
        <item_description>(Specific to application 001)</item_description>
      </item>
      <item>
        <item_name>Detergent 3</item_name>
        <item_description>(Specific to application 001)</item_description>
      </item>
    </items>
  </step>
  <step id="step_4">
    <step_no>4</step_no>
    <step_title>Procedure</step_title>
    <substep id="substep_4_1">
      <substep_no>4.1</substep_no>
      <substep_title>1. Initial Cleaning</substep_title>
      <items>
        <item>Rinse the bicycle with water to remove loose dirt and debris. Refer to Figure 1 for visual guidance.</item>
        <item>Use a brush to scrub hard-to-reach areas like shift levers, tires, and brakes.</item>
      </items>
      <figure>
        <figure_title>Cleaning the Bike</figure_title>
        <figure_source>ICN-C0419-S1000D0359-001-01</figure_source>
      </figure>
    </substep>
    <substep id="substep_4_2">
      <substep_no>4.2</substep_no>
      <substep_title>2. Grime Removal</substep_title>
      <items>
        <item>Use a small blade screwdriver to remove caked grime from the chain and sprockets.</item>
        <item>Brush the following parts to remove grease:</item>
        <item>Sprockets</item>
        <item>Guide and tension wheels of the derailleur</item>
        <item>Chain ring teeth</item>
        <item>Flush the sprockets, derailleurs, chain rings, and chain with water. Repeat if necessary.</item>
      </items>
    </substep>
    <substep id="substep_4_3">
      <substep_no>4.3</substep_no>
      <substep_title>3. Degreasing (Freehub)</substep_title>
      <items>
        <item>Refer to Figure 2 for guidance on degreasing the freehub.</item>
      </items>
      <figure>
        <figure_title>Degreasing the Freehub</figure_title>
        <figure_source>ICN-C0419-S1000D0400-001-01</figure_source>
      </figure>
    </substep>
    <substep id="substep_4_4">
      <substep_no>4.4</substep_no>
      <substep_title>4. Washing (Application-Specific)</substep_title>
      <items>
        <item>Note: The following steps vary based on bicycle application.</item>
      </items>
      <subsubstep id="subsubstep_4_4_1">
        <subsubstep_no>4.4.1</subsubstep_no>
        <subsubstep_title>Application 002</subsubstep_title>
        <items>
          <item>Soak a sponge in Detergent 2 and water.</item>
          <item>Clean the bicycle with the soaked sponge.</item>
          <item>Flush the bicycle to remove detergent residue.</item>
          <item>Move the bicycle up and down on its tires to remove excess water.</item>
        </items>
      </subsubstep>
      <subsubstep id="subsubstep_4_4_2">
        <subsubstep_no>4.4.2</subsubstep_no>
        <subsubstep_title>Application 001</subsubstep_title>
        <items>
          <item>Soak a sponge in Detergent 3 and water.</item>
          <item>Clean the bicycle with the soaked sponge.</item>
          <item>Soak a sponge in Detergent 2 and water.</item>
          <item>Clean the bicycle with the soaked sponge.</item>
          <item>Flush the bicycle to remove detergent residue.</item>
          <item>Move the bicycle up and down on its tires to remove excess water.</item>
        </items>
      </subsubstep>
    </substep>
    <substep id="substep_4_5">
      <substep_no>4.5</substep_no>
      <substep_title>5. Lubrication</substep_title>
      <items>
        <item>Refer to the Data Module (S1000DBIKE, System DA4, etc.) for specific lubricant recommendations.</item>
      </items>
    </substep>
  </step>
  <step id="step_5">
    <step_no>5</step_no>
    <step_title>Completion Requirements</step_title>
    <items>
      <item>Ensure the bicycle is completely dry before storage or use.</item>
    </items>
  </step>
  <step id="step_6">
    <step_no>6</step_no>
    <step_title>Data Module Reference</step_title>
    <items>
      <item>Data Module: [S1000DBIKE, System DA4, etc. - Refer to document for details]</item>
    </items>
  </step>
</procedure>