<?xml version="1.0" encoding="UTF-8"?>
<Content xmlns:dc="http://www.purl.org/dc/elements/1.1/" xmlns:rdf="http://www.w3.org/1999/02/22-rdf-syntax-ns#" xmlns:xlink="http://www.w3.org/1999/xlink" xmlns:xsi="http://www.w3.org/2001/XMLSchema-instance" xsi:noNamespaceSchemaLocation="http://www.s1000d.org/S1000D_6/xml_schema_flat/proced.xsd">
  <IdentAndStatusSection>
    <GeneralInformation>
      <DocumentTitle>DMC-S1000DBIKE-AAA-DA0-30-00-00AA-520A-A_004-00</DocumentTitle>
      <DocumentType>Content</DocumentType>
    </GeneralInformation>
    <Status>
      <QualityAssurance>First Verification (Tab Top)</QualityAssurance>
      <SystemBreakdownCode>BY</SystemBreakdownCode>
      <SkillLevel>sk01</SkillLevel>
      <ReasonForUpdate rdf:about="">
        <RfuGeneral>S1000D upissued</RfuGeneral>
        <RfuFig01>Figure added</RfuFig01>
      </ReasonForUpdate>
    </Status>
  </IdentAndStatusSection>
  <ContentSection>
    <ReferencedApplicGroup>
      <Application rdf:about="">
        <Id>app-0002</Id>
        <DisplayText>Mountain bicycle and Mountain storm Mk1</DisplayText>
        <Evaluation>Type = Mountain bicycle AND Model = Mountain storm</Evaluation>
      </Application>
      <Application rdf:about="">
        <Id>app-0003</Id>
        <DisplayText>Mountain bicycle and Brook trekker Mk9</DisplayText>
        <Evaluation>Type = Mountain bicycle AND Model = Brook trekker</Evaluation>
      </Application>
    </ReferencedApplicGroup>
    <WarningsAndCautions>
      <Caution rdf:about="">
        <Id>C0001</Id>
        <WarningCautionParagraph>Be sure to operate on a white surface in order to prevent lost of part that could fall on the floor.</WarningCautionParagraph>
      </Caution>
    </WarningsAndCautions>
    <ProcedureSection>
      <PreliminaryRequirements>
        <NoCondition>No conditions specified.</NoCondition>
        <Personnel>No personnel specified.</Personnel>
        <SupportEquipment>
          <Name>Specialist toolset</Name>
          <Identification>
            <ManufacturerCode>KZ666</ManufacturerCode>
            <PartNumber>BSK-TLST-001</PartNumber>
          </Identification>
          <RequiredQuantity>1 EA</RequiredQuantity>
        </SupportEquipment>
        <Supplies>
          <Supply rdf:about="">
            <ReferenceId>SPEC-0012</ReferenceId>
            <SupplyNumber>BKO200</SupplyNumber>
            <SupplyNumberType>sp01</SupplyNumberType>
            <Name>BIKOIL 200</Name>
            <RequiredQuantity>As Required</RequiredQuantity>
          </Supply>
          <Supply rdf:about="">
            <ReferenceId>SPEC-0013</ReferenceId>
            <SupplyRequirementNumber>EU-OIL3212</SupplyRequirementNumber>
            <RequiredQuantity>As Required</RequiredQuantity>
          </Supply>
        </Supplies>
        <Spares>No spares specified.</Spares>
        <Safety>No safety requirements specified.</Safety>
      </PreliminaryRequirements>
      <MainProcedure>
        <Step rdf:about="">
          <StepNumber>1</StepNumber>
          <StepText>Open the light circuit breaker located on the handlebar.</StepText>
          <CircuitBreakerDetails rdf:about="">
            <Id>SPEC-0001</Id>
            <CircuitBreakerNumber>CBLGT-1001-R</CircuitBreakerNumber>
            <Name>Bike Lighting circuit breaker (right side)</Name>
            <AccessPointNumber>any-access</AccessPointNumber>
            <Location>Zone 131</Location>
            <Action>open</Action>
          </CircuitBreakerDetails>
          <CircuitBreakerDetails rdf:about="">
            <Id>SPEC-0002</Id>
            <CircuitBreakerNumber>CBLGT-1001-L</CircuitBreakerNumber>
            <Name>Bike Lighting circuit breaker (left side)</Name>
            <AccessPointNumber>any-access</AccessPointNumber>
            <Location>Zone 132</Location>
            <Action>open</Action>
          </CircuitBreakerDetails>
        </Step>
        <Step rdf:about="">
          <StepNumber>2</StepNumber>
          <StepText>Hold the front of the bicycle.</StepText>
        </Step>
        <Step rdf:about="">
          <StepNumber>3</StepNumber>
          <StepText>Use the (sequence 0001) to disengage the fork from the chainring by pushing the wheel forwards and down. *(Caution Reference: C0001)*</StepText>
          <Figure>
            <Id>SPEC-0010</Id>
            <InfoEntityIdent>ICN-C0419-S1000D0372-001-01</InfoEntityIdent>
            <ReasonForAmendment>Addition of the wheel illustration</ReasonForAmendment>
          </Figure>
          <SupplyReference>Use specific oil (SPEC-0012) if the fork do not desengage easily. If not available, use any oil compliant with requirements (SPEC-0013).</SupplyReference>
        </Step>
        <Step rdf:about="">
          <StepNumber>4</StepNumber>
          <StepText>Lift the wheel away from the frame.</StepText>
        </Step>
        <Step rdf:about="">
          <StepNumber>5</StepNumber>
          <StepText>Put the frame on the floor.</StepText>
        </Step>
      </MainProcedure>
    </ProcedureSection>
  </ContentSection>
  <CloseRequirements>
    <NoCondition>No conditions specified.</NoCondition>
  </CloseRequirements>
</Content>