<?xml version="1.0" encoding="UTF-8"?>
<dmc:dmc xmlns:dmc="http://www.s1000d.org/S1000D_6/dmc_6" xmlns:xsi="http://www.w3.org/2001/XMLSchema-instance" xmlns:dc="http://www.purl.org/dc/elements/1.1/" xmlns:rdf="http://www.w3.org/1999/02/22-rdf-syntax-ns#" xmlns:xlink="http://www.w3.org/1999/xlink" xsi:schemaLocation="http://www.s1000d.org/S1000D_6/dmc_6 dmc6.xsd" xsi:noNamespaceSchemaLocation="http://www.s1000d.org/S1000D_6/xml_schema_flat/proced.xsd">
  <dmc:dms>
    <dmc:dm>
      <dmc:ident>
        <dmc:modelIdentCode>S1000DBIKE</dmc:modelIdentCode>
        <dmc:systemDiffCode>AAA</dmc:systemDiffCode>
        <dmc:systemCode>D00</dmc:systemCode>
        <dmc:subSystemCode>0</dmc:subSystemCode>
        <dmc:subSubSystemCode>0</dmc:subSubSystemCode>
        <dmc:assyCode>00</dmc:assyCode>
        <dmc:disassyCode>00</dmc:disassyCode>
        <dmc:disassyCodeVariant>AA</dmc:disassyCodeVariant>
        <dmc:infoCode>043</dmc:infoCode>
        <dmc:itemLocationCode>A</dmc:itemLocationCode>
      </dmc:ident>
      <dmc:status>
        <dmc:reasonForUpdate>S1000D upissued</dmc:reasonForUpdate>
        <dmc:qualityAssurance>tabtop</dmc:qualityAssurance>
        <dmc:systemBreakdownCode>BY</dmc:systemBreakdownCode>
        <dmc:skillLevel>sk01</dmc:skillLevel>
      </dmc:status>
      <dmc:content>
        <dmc:ref>
          <dmc:modelIdentCode>S1000DBIKE</dmc:modelIdentCode>
          <dmc:systemDiffCode>AAA</dmc:systemDiffCode>
          <dmc:systemCode>DA5</dmc:systemCode>
          <dmc:subSystemCode>3</dmc:subSystemCode>
          <dmc:subSubSystemCode>0</dmc:subSubSystemCode>
          <dmc:assyCode>00</dmc:assyCode>
          <dmc:disassyCode>00</dmc:disassyCode>
          <dmc:disassyCodeVariant>AA</dmc:disassyCodeVariant>
          <dmc:infoCode>041</dmc:infoCode>
          <dmc:itemLocationCode>A</dmc:itemLocationCode>
        </dmc:ref>
        <dmc:crew>
          <dmc:descrCrew>
            <dmc:introduction>Data about the bicycle and its control system is given in this document. This data will help you operate the bicycle.</dmc:introduction>
            <dmc:controls>Data about the controls that follow is given in this document:
              <dmc:bullet>Steering</dmc:bullet>
              <dmc:bullet>Shifters</dmc:bullet>
              <dmc:bullet>Brakes</dmc:bullet>
              <dmc:bullet>Pedals</dmc:bullet>
            </dmc:controls>
            <dmc:steering>The handlebars are used to steer the bike. They are at the front of the bicycle. You hold one of the handlebar grips with each hand and move the handle bar to change the direction of the bike.</dmc:steering>
            <dmc:shifters>The gears control the ratio of pedal rotation to wheel rotation. You can change this with the shifters. The shifters are on the handlebar.</dmc:shifters>
            <dmc:shiftersTable>
              <dmc:tableHeader>
                <dmc:tableCell>Shifter Location</dmc:tableCell>
                <dmc:tableCell>Affected Gears</dmc:tableCell>
              </dmc:tableHeader>
              <dmc:tableRow>
                <dmc:tableCell>Left</dmc:tableCell>
                <dmc:tableCell>The buttons on the left shifter changes the gears on the front derailleur.</dmc:tableCell>
              </dmc:tableRow>
              <dmc:tableRow>
                <dmc:tableCell>Right</dmc:tableCell>
                <dmc:tableCell>The buttons on the right shifter changes the gears on the rear derailleur.</dmc:tableCell>
              </dmc:tableRow>
            </dmc:shiftersTable>
            <dmc:brakes>
              <dmc:warning>If you operate the front brake without the rear brake you can cause a crash.</dmc:warning>
              <dmc:description>You can decrease the speed of the bike with the brakes. You operate the brakes with the brake levers on the handlebar.</dmc:description>
            </dmc:brakes>
            <dmc:brakesTable>
              <dmc:tableHeader>
                <dmc:tableCell>Brake Lever Location</dmc:tableCell>
                <dmc:tableCell>Affected Brake</dmc:tableCell>
              </dmc:tableHeader>
              <dmc:tableRow>
                <dmc:tableCell>Left</dmc:tableCell>
                <dmc:tableCell>This lever operates the front brake.</dmc:tableCell>
              </dmc:tableRow>
              <dmc:tableRow>
                <dmc:tableCell>Right</dmc:tableCell>
                <dmc:tableCell>This lever operates the rear brake.</dmc:tableCell>
              </dmc:tableRow>
            </dmc:brakesTable>
            <dmc:pedals>The pedals are at the bottom of the seat tube. You operate the pedals to move the bicycle forward.</dmc:pedals>
          </dmc:descrCrew>
        </dmc:crew>
      </dmc:content>
    </dmc:dm>
  </dmc:dms>
</dmc:dmc>